<?xml version="1.0" encoding="UTF-8"?>
<MetaDataObject xmlns="http://v8.1c.ru/8.3/MDClasses" xmlns:app="http://v8.1c.ru/8.2/managed-application/core" xmlns:cfg="http://v8.1c.ru/8.1/data/enterprise/current-config" xmlns:cmi="http://v8.1c.ru/8.2/managed-application/cmi" xmlns:ent="http://v8.1c.ru/8.1/data/enterprise" xmlns:lf="http://v8.1c.ru/8.2/managed-application/logform" xmlns:style="http://v8.1c.ru/8.1/data/ui/style" xmlns:sys="http://v8.1c.ru/8.1/data/ui/fonts/system" xmlns:v8="http://v8.1c.ru/8.1/data/core" xmlns:v8ui="http://v8.1c.ru/8.1/data/ui" xmlns:web="http://v8.1c.ru/8.1/data/ui/colors/web" xmlns:win="http://v8.1c.ru/8.1/data/ui/colors/windows" xmlns:xen="http://v8.1c.ru/8.3/xcf/enums" xmlns:xpr="http://v8.1c.ru/8.3/xcf/predef" xmlns:xr="http://v8.1c.ru/8.3/xcf/readable" xmlns:xs="http://www.w3.org/2001/XMLSchema" xmlns:xsi="http://www.w3.org/2001/XMLSchema-instance" version="2.17">
	<HTTPService uuid="5a86557b-7e7a-4c4b-ad5b-4f6790544c82">
		<Properties>
			<Name>Responses</Name>
			<Synonym>
				<v8:item>
					<v8:lang>ru</v8:lang>
					<v8:content>Раздел "Возвращаемые ответы"</v8:content>
				</v8:item>
			</Synonym>
			<Comment/>
			<RootURL>Responses</RootURL>
			<ReuseSessions>AutoUse</ReuseSessions>
			<SessionMaxAge>20</SessionMaxAge>
		</Properties>
		<ChildObjects>
			<URLTemplate uuid="e6708ca5-ad2f-4abe-baf5-062449015340">
				<Properties>
					<Name>Variants</Name>
					<Synonym>
						<v8:item>
							<v8:lang>ru</v8:lang>
							<v8:content>Variants</v8:content>
						</v8:item>
					</Synonym>
					<Comment/>
					<Template>/Variants</Template>
				</Properties>
				<ChildObjects>
					<Method uuid="25062d10-e210-4cd9-b10f-dae8f1a36071">
						<Properties>
							<Name>GET</Name>
							<Synonym>
								<v8:item>
									<v8:lang>ru</v8:lang>
									<v8:content>Возвращаемые ответы</v8:content>
								</v8:item>
							</Synonym>
							<Comment/>
							<HTTPMethod>GET</HTTPMethod>
							<Handler>VariantsGET</Handler>
						</Properties>
					</Method>
					<Method uuid="c026e94e-d9ac-4823-babc-f2b36e66eb24">
						<Properties>
							<Name>POST</Name>
							<Synonym>
								<v8:item>
									<v8:lang>ru</v8:lang>
									<v8:content>Один код состояния - несколько ответов</v8:content>
								</v8:item>
							</Synonym>
							<Comment/>
							<HTTPMethod>POST</HTTPMethod>
							<Handler>VariantsPOST</Handler>
						</Properties>
					</Method>
				</ChildObjects>
			</URLTemplate>
		</ChildObjects>
	</HTTPService>
</MetaDataObject>